{
    "dark": [
        "#101010",
        "#101010"
    ],
    "grey": [
        "#363636",
        "#363636"
    ],
    "light": [
        "#cccdd1",
        "#cccdd1"
    ],
    "text": [
        "#1e1e1e",
        "#1e1e1e"
    ],
    "focus": [
        "#ff77a8",
        "#ff77a8"
    ],
    "urgent": [
        "#ff1a67",
        "#ff1a67"
    ],
    "active": [
        "#29adff",
        "#29adff"
    ],
    "inactive": [
        "#252525",
        "#252525"
    ],
    "color1": [
        "#ffa300",
        "#ffa300"
    ],
    "color2": [
        "#a79ac0",
        "#a79ac0"
    ],
    "color3": [
        "#29adff",
        "#29adff"
    ],
    "color4": [
        "#fff024",
        "#fff024"
    ]
}
